romaniya_menim/__init__.py
romaniya_menim/classifiers.py
romaniya_menim/dataloaders.py
romaniya_menim/utils.py
romaniya_menim/data/ACSF1_TEST.tsv
romaniya_menim/data/ACSF1_TRAIN.tsv
romaniya_menim/data/Adiac_TEST.tsv
romaniya_menim/data/Adiac_TRAIN.tsv
romaniya_menim/data/AllGestureWiimoteX_TEST.tsv
romaniya_menim/data/AllGestureWiimoteX_TRAIN.tsv
romaniya_menim/data/AllGestureWiimoteY_TEST.tsv
romaniya_menim/data/AllGestureWiimoteY_TRAIN.tsv
romaniya_menim/data/AllGestureWiimoteZ_TEST.tsv
romaniya_menim/data/AllGestureWiimoteZ_TRAIN.tsv
romaniya_menim/data/ArrowHead_TEST.tsv
romaniya_menim/data/ArrowHead_TRAIN.tsv
romaniya_menim/data/BME_TEST.tsv
romaniya_menim/data/BME_TRAIN.tsv
romaniya_menim/data/Beef_TEST.tsv
romaniya_menim/data/Beef_TRAIN.tsv
romaniya_menim/data/BeetleFly_TEST.tsv
romaniya_menim/data/BeetleFly_TRAIN.tsv
romaniya_menim/data/BirdChicken_TEST.tsv
romaniya_menim/data/BirdChicken_TRAIN.tsv
romaniya_menim/data/CBF_TEST.tsv
romaniya_menim/data/CBF_TRAIN.tsv
romaniya_menim/data/Car_TEST.tsv
romaniya_menim/data/Car_TRAIN.tsv
romaniya_menim/data/Chinatown_TEST.tsv
romaniya_menim/data/Chinatown_TRAIN.tsv
romaniya_menim/data/ChlorineConcentration_TEST.tsv
romaniya_menim/data/ChlorineConcentration_TRAIN.tsv
romaniya_menim/data/CinCECGTorso_TEST.tsv
romaniya_menim/data/CinCECGTorso_TRAIN.tsv
romaniya_menim/data/Coffee_TEST.tsv
romaniya_menim/data/Coffee_TRAIN.tsv
romaniya_menim/data/Computers_TEST.tsv
romaniya_menim/data/Computers_TRAIN.tsv
romaniya_menim/data/__init__.py
romaniya_menim/models/__init__.py
romaniya_menim/models/cnn.py
romaniya_menim/models/fcn.py
romaniya_menim/models/inception.py
romaniya_menim/models/mlp.py
romaniya_menim/models/resnet.py
romaniya_menim-0.0.34.dist-info/METADATA
romaniya_menim-0.0.34.dist-info/WHEEL
romaniya_menim-0.0.34.dist-info/top_level.txt
romaniya_menim-0.0.34.dist-info/RECORD
